cdktf_infra_uniovi/__init__.py
cdktf_infra_uniovi/py.typed
cdktf_infra_uniovi/_jsii/__init__.py
cdktf_infra_uniovi/_jsii/cdktf-infra-uniovi@0.0.5.jsii.tgz
cdktf_infra_uniovi-0.0.5.dist-info/LICENSE
cdktf_infra_uniovi-0.0.5.dist-info/METADATA
cdktf_infra_uniovi-0.0.5.dist-info/WHEEL
cdktf_infra_uniovi-0.0.5.dist-info/top_level.txt
cdktf_infra_uniovi-0.0.5.dist-info/RECORD
