Metadata-Version: 2.1
Name: cdktf-infra-uniovi
Version: 0.0.5
Summary: cdktf-infra-uniovi
Home-page: https://github.com/Yori1999/cdktf-infra-uniovi.git
Author: María Flórez<mariaf987@gmail.com>
License: Apache-2.0
Project-URL: Source, https://github.com/Yori1999/cdktf-infra-uniovi.git
Classifier: Intended Audience :: Developers
Classifier: Operating System :: OS Independent
Classifier: Programming Language :: JavaScript
Classifier: Programming Language :: Python :: 3 :: Only
Classifier: Programming Language :: Python :: 3.9
Classifier: Programming Language :: Python :: 3.10
Classifier: Programming Language :: Python :: 3.11
Classifier: Typing :: Typed
Classifier: Development Status :: 5 - Production/Stable
Classifier: License :: OSI Approved
Requires-Python: ~=3.9
License-File: LICENSE
Requires-Dist: cdktf-cdktf-provider-aws<20.0.0,>=19.0.0
Requires-Dist: cdktf-cdktf-provider-docker<12.0.0,>=11.0.0
Requires-Dist: cdktf<0.21.0,>=0.20.11
Requires-Dist: constructs<11.0.0,>=10.3.0
Requires-Dist: jsii<2.0.0,>=1.112.0
Requires-Dist: publication>=0.0.3
Requires-Dist: typeguard<4.3.0,>=2.13.3
